flipflop/flipflop.v
module flipflop (
    input wire reset,
    input wire clk,
    input wire set,
    input wire enable,
	input wire d,
    output reg q
);
always @ (posedge clk or posedge reset)
    if (reset)
       q <= 1'b0;
    else
    if(set)
	   q <= 1'b1;
	else 
	if (enable)
	   q <= d;
endmodule

flipflop/tflipflop.v
module test_flipflop;

reg reset, clk, enable, set, d;
wire q;

//устанавливаем экземпляр тестируемого модуля
flipflop flipflop_inst(reset, clk, set, enable, d, q);

//моделируем сигнал тактовой частоты
always
  #5 clk = ~clk;

//от начала времени...

initial
begin
  clk = 0;
  reset = 0;
  d = 0;
  set = 0;
  enable = 0;

//через временной интервал "50" подаем сигнал сброса
  #50 reset = 1;

//еще через время "4" снимаем сигнал сброса

  #4 reset = 0;

//пауза длительностью "50"
  #50;

//ждем фронта тактовой частоты и сразу после нее подаем сигнал записи
  @(posedge clk)
  #0    
      d = 1'b1;
  #50 
//по следующему фронту снимаем сигнал записи
  @(posedge clk)
  #0
      enable = 1;
  #40  
      reset = 1;
  #5  reset = 0;	  
  #40
  @(posedge clk)
  begin
  enable = 0;
  #20
  d = 0;
  end
  #20
  enable = 1;
  #40
  @(posedge clk)
  begin
  set = 1;
  #3
  set = 0;
  end
  
  
  
end

//заканчиваем симуляцию в момент времени "400"
initial
begin
  #1000 $finish;
end

//создаем файл VCD для последующего анализа сигналов
initial
begin
  $dumpfile("out.vcd");
  $dumpvars(0,test_flipflop);
end

//наблюдаем на некоторыми сигналами системы
initial
$monitor($stime,, reset,, clk,,, d,, enable,, q,, set);

endmodule

flipflop/out.vcd
$date
	Mon Aug 03 21:50:04 2020
$end
$version
	Icarus Verilog
$end
$timescale
	1s
$end
$scope module test_flipflop $end
$var wire 1 ! q $end
$var reg 1 " clk $end
$var reg 1 # d $end
$var reg 1 $ enable $end
$var reg 1 % reset $end
$var reg 1 & set $end
$scope module flipflop_inst $end
$var wire 1 " clk $end
$var wire 1 # d $end
$var wire 1 $ enable $end
$var wire 1 % reset $end
$var wire 1 & set $end
$var reg 1 ! q $end
$upscope $end
$upscope $end
$enddefinitions $end
#0
$dumpvars
0&
0%
0$
0#
0"
x!
$end
#5
1"
#10
0"
#15
1"
#20
0"
#25
1"
#30
0"
#35
1"
#40
0"
#45
1"
#50
0!
0"
1%
#54
0%
#55
1"
#60
0"
#65
1"
#70
0"
#75
1"
#80
0"
#85
1"
#90
0"
#95
1"
#100
0"
#105
1#
1"
#110
0"
#115
1"
#120
0"
#125
1"
#130
0"
#135
1"
#140
0"
#145
1"
#150
0"
#155
1$
1"
#160
0"
#165
1!
1"
#170
0"
#175
1"
#180
0"
#185
1"
#190
0"
#195
0!
1"
1%
#200
0"
0%
#205
1!
1"
#210
0"
#215
1"
#220
0"
#225
1"
#230
0"
#235
1"
#240
0"
#245
0$
1"
#250
0"
#255
1"
#260
0"
#265
1"
0#
#270
0"
#275
1"
#280
0"
#285
0!
1"
1$
#290
0"
#295
1"
#300
0"
#305
1"
#310
0"
#315
1"
#320
0"
#325
1!
1&
1"
#328
0&
#330
0"
#335
0!
1"
